[
  {
    "year": 2014,
    "filter": "all",
    "['Manufacturing']": 325.3,
    "['Technology']": 685.19,
    "['Real Estate']": 442.9,
    "['Fashion & Retail']": 684.2,
    "['Diversified']": 512.25,
    "['Finance & Investments']": 0.0,
    "['Finance and Investments']": 401.8,
    "['Healthcare']": 142.5,
    "['Energy']": 421.75,
    "['Food and Beverage']": 448.95
  },
  {
    "year": 2014,
    "filter": "self-made",
    "['Manufacturing']": 187.9,
    "['Technology']": 640.89,
    "['Real Estate']": 309.8,
    "['Fashion & Retail']": 338.25,
    "['Diversified']": 217.15,
    "['Finance & Investments']": 0.0,
    "['Finance and Investments']": 272.15,
    "['Healthcare']": 98.35,
    "['Energy']": 291.5,
    "['Food and Beverage']": 178.6
  },
  {
    "year": 2014,
    "filter": "inherited",
    "['Manufacturing']": 137.4,
    "['Technology']": 44.3,
    "['Real Estate']": 133.1,
    "['Fashion & Retail']": 345.95,
    "['Diversified']": 295.1,
    "['Finance & Investments']": 0.0,
    "['Finance and Investments']": 129.65,
    "['Healthcare']": 44.15,
    "['Energy']": 130.25,
    "['Food and Beverage']": 270.35
  },
  {
    "year": 2015,
    "filter": "all",
    "['Manufacturing']": 365.35,
    "['Technology']": 808.75,
    "['Real Estate']": 535.7,
    "['Fashion & Retail']": 903.35,
    "['Diversified']": 563.33,
    "['Finance & Investments']": 0.0,
    "['Finance and Investments']": 679.3,
    "['Healthcare']": 275.2,
    "['Energy']": 397.55,
    "['Food and Beverage']": 542.35
  },
  {
    "year": 2015,
    "filter": "self-made",
    "['Manufacturing']": 212.15,
    "['Technology']": 757.4,
    "['Real Estate']": 374.65,
    "['Fashion & Retail']": 416.1,
    "['Diversified']": 238.1,
    "['Finance & Investments']": 0.0,
    "['Finance and Investments']": 460.15,
    "['Healthcare']": 174.0,
    "['Energy']": 272.4,
    "['Food and Beverage']": 209.25
  },
  {
    "year": 2015,
    "filter": "inherited",
    "['Manufacturing']": 153.2,
    "['Technology']": 51.35,
    "['Real Estate']": 161.05,
    "['Fashion & Retail']": 487.25,
    "['Diversified']": 325.23,
    "['Finance & Investments']": 0.0,
    "['Finance and Investments']": 219.15,
    "['Healthcare']": 101.2,
    "['Energy']": 125.15,
    "['Food and Beverage']": 333.1
  },
  {
    "year": 2016,
    "filter": "all",
    "['Manufacturing']": 379.6,
    "['Technology']": 819.7,
    "['Real Estate']": 538.5,
    "['Fashion & Retail']": 969.0,
    "['Diversified']": 518.6,
    "['Finance & Investments']": 0.0,
    "['Finance and Investments']": 884.0,
    "['Healthcare']": 303.5,
    "['Energy']": 289.9,
    "['Food and Beverage']": 516.0
  },
  {
    "year": 2016,
    "filter": "self-made",
    "['Manufacturing']": 231.5,
    "['Technology']": 768.5,
    "['Real Estate']": 396.3,
    "['Fashion & Retail']": 425.8,
    "['Diversified']": 230.3,
    "['Finance & Investments']": 0.0,
    "['Finance and Investments']": 675.3,
    "['Healthcare']": 195.8,
    "['Energy']": 190.5,
    "['Food and Beverage']": 196.7
  },
  {
    "year": 2016,
    "filter": "inherited",
    "['Manufacturing']": 148.1,
    "['Technology']": 51.2,
    "['Real Estate']": 142.2,
    "['Fashion & Retail']": 543.2,
    "['Diversified']": 288.3,
    "['Finance & Investments']": 0.0,
    "['Finance and Investments']": 208.7,
    "['Healthcare']": 107.7,
    "['Energy']": 99.4,
    "['Food and Beverage']": 319.3
  },
  {
    "year": 2017,
    "filter": "all",
    "['Manufacturing']": 479.3,
    "['Technology']": 1002.5,
    "['Real Estate']": 621.3,
    "['Fashion & Retail']": 1041.3,
    "['Diversified']": 661.0,
    "['Finance & Investments']": 0.0,
    "['Finance and Investments']": 1032.3,
    "['Healthcare']": 324.9,
    "['Energy']": 373.8,
    "['Food and Beverage']": 561.8
  },
  {
    "year": 2017,
    "filter": "self-made",
    "['Manufacturing']": 303.6,
    "['Technology']": 962.2,
    "['Real Estate']": 451.8,
    "['Fashion & Retail']": 475.2,
    "['Diversified']": 290.7,
    "['Finance & Investments']": 0.0,
    "['Finance and Investments']": 796.2,
    "['Healthcare']": 205.5,
    "['Energy']": 248.2,
    "['Food and Beverage']": 231.2
  },
  {
    "year": 2017,
    "filter": "inherited",
    "['Manufacturing']": 175.7,
    "['Technology']": 40.3,
    "['Real Estate']": 169.5,
    "['Fashion & Retail']": 566.1,
    "['Diversified']": 370.3,
    "['Finance & Investments']": 0.0,
    "['Finance and Investments']": 236.1,
    "['Healthcare']": 119.4,
    "['Energy']": 125.6,
    "['Food and Beverage']": 330.6
  },
  {
    "year": 2018,
    "filter": "all",
    "['Manufacturing']": 612.7,
    "['Technology']": 1273.8,
    "['Real Estate']": 787.9,
    "['Fashion & Retail']": 1192.3,
    "['Diversified']": 777.1,
    "['Finance & Investments']": 4.1,
    "['Finance and Investments']": 1138.4,
    "['Healthcare']": 387.3,
    "['Energy']": 400.8,
    "['Food and Beverage']": 678.1
  },
  {
    "year": 2018,
    "filter": "self-made",
    "['Manufacturing']": 394.7,
    "['Technology']": 1224.8,
    "['Real Estate']": 578.0,
    "['Fashion & Retail']": 526.9,
    "['Diversified']": 319.8,
    "['Finance & Investments']": 4.1,
    "['Finance and Investments']": 864.0,
    "['Healthcare']": 257.7,
    "['Energy']": 260.7,
    "['Food and Beverage']": 285.7
  },
  {
    "year": 2018,
    "filter": "inherited",
    "['Manufacturing']": 218.0,
    "['Technology']": 49.0,
    "['Real Estate']": 209.9,
    "['Fashion & Retail']": 665.4,
    "['Diversified']": 457.3,
    "['Finance & Investments']": 0.0,
    "['Finance and Investments']": 274.4,
    "['Healthcare']": 129.6,
    "['Energy']": 140.1,
    "['Food and Beverage']": 392.4
  },
  {
    "year": 2019,
    "filter": "all",
    "['Manufacturing']": 536.9,
    "['Technology']": 1301.3,
    "['Real Estate']": 774.6,
    "['Fashion & Retail']": 1159.4,
    "['Diversified']": 699.9,
    "['Finance & Investments']": 1.5,
    "['Finance and Investments']": 1102.3,
    "['Healthcare']": 370.4,
    "['Energy']": 414.8,
    "['Food and Beverage']": 660.8
  },
  {
    "year": 2019,
    "filter": "self-made",
    "['Manufacturing']": 344.5,
    "['Technology']": 1250.5,
    "['Real Estate']": 561.5,
    "['Fashion & Retail']": 504.0,
    "['Diversified']": 279.7,
    "['Finance & Investments']": 0.0,
    "['Finance and Investments']": 843.3,
    "['Healthcare']": 245.7,
    "['Energy']": 271.4,
    "['Food and Beverage']": 272.7
  },
  {
    "year": 2019,
    "filter": "inherited",
    "['Manufacturing']": 192.4,
    "['Technology']": 50.8,
    "['Real Estate']": 213.1,
    "['Fashion & Retail']": 655.4,
    "['Diversified']": 420.2,
    "['Finance & Investments']": 1.5,
    "['Finance and Investments']": 259.0,
    "['Healthcare']": 124.7,
    "['Energy']": 143.4,
    "['Food and Beverage']": 388.1
  },
  {
    "year": 2020,
    "filter": "all",
    "['Manufacturing']": 540.6,
    "['Technology']": 1357.9,
    "['Real Estate']": 642.4,
    "['Fashion & Retail']": 1122.9,
    "['Diversified']": 556.6,
    "['Finance & Investments']": 1022.2,
    "['Finance and Investments']": 0.0,
    "['Healthcare']": 425.7,
    "['Energy']": 326.6,
    "['Food and Beverage']": 0.0
  },
  {
    "year": 2020,
    "filter": "self-made",
    "['Manufacturing']": 372.4,
    "['Technology']": 1269.8,
    "['Real Estate']": 467.2,
    "['Fashion & Retail']": 462.3,
    "['Diversified']": 235.2,
    "['Finance & Investments']": 818.6,
    "['Finance and Investments']": 0.0,
    "['Healthcare']": 310.9,
    "['Energy']": 221.6,
    "['Food and Beverage']": 0.0
  },
  {
    "year": 2020,
    "filter": "inherited",
    "['Manufacturing']": 168.2,
    "['Technology']": 88.1,
    "['Real Estate']": 175.2,
    "['Fashion & Retail']": 660.6,
    "['Diversified']": 321.4,
    "['Finance & Investments']": 203.6,
    "['Finance and Investments']": 0.0,
    "['Healthcare']": 114.8,
    "['Energy']": 105.0,
    "['Food and Beverage']": 0.0
  },
  {
    "year": 2021,
    "filter": "all",
    "['Manufacturing']": 1119.9,
    "['Technology']": 2453.3,
    "['Real Estate']": 815.8,
    "['Fashion & Retail']": 1697.6,
    "['Diversified']": 868.1,
    "['Finance & Investments']": 1529.1,
    "['Finance and Investments']": 0.0,
    "['Healthcare']": 790.7,
    "['Energy']": 406.3,
    "['Food and Beverage']": 0.0
  },
  {
    "year": 2021,
    "filter": "self-made",
    "['Manufacturing']": 829.0,
    "['Technology']": 2325.1,
    "['Real Estate']": 580.0,
    "['Fashion & Retail']": 737.4,
    "['Diversified']": 364.1,
    "['Finance & Investments']": 1215.3,
    "['Finance and Investments']": 0.0,
    "['Healthcare']": 604.3,
    "['Energy']": 322.2,
    "['Food and Beverage']": 0.0
  },
  {
    "year": 2021,
    "filter": "inherited",
    "['Manufacturing']": 290.9,
    "['Technology']": 128.2,
    "['Real Estate']": 235.8,
    "['Fashion & Retail']": 960.2,
    "['Diversified']": 504.0,
    "['Finance & Investments']": 313.8,
    "['Finance and Investments']": 0.0,
    "['Healthcare']": 186.4,
    "['Energy']": 84.1,
    "['Food and Beverage']": 0.0
  },
  {
    "year": 2022,
    "filter": "all",
    "['Manufacturing']": 1094.8,
    "['Technology']": 2165.7,
    "['Real Estate']": 689.8,
    "['Fashion & Retail']": 1617.2,
    "['Diversified']": 941.5,
    "['Finance & Investments']": 1740.3,
    "['Finance and Investments']": 0.0,
    "['Healthcare']": 713.9,
    "['Energy']": 396.2,
    "['Food and Beverage']": 0.0
  },
  {
    "year": 2022,
    "filter": "self-made",
    "['Manufacturing']": 794.8,
    "['Technology']": 2048.2,
    "['Real Estate']": 471.7,
    "['Fashion & Retail']": 669.0,
    "['Diversified']": 396.6,
    "['Finance & Investments']": 1404.4,
    "['Finance and Investments']": 0.0,
    "['Healthcare']": 510.0,
    "['Energy']": 296.8,
    "['Food and Beverage']": 0.0
  },
  {
    "year": 2022,
    "filter": "inherited",
    "['Manufacturing']": 300.0,
    "['Technology']": 117.5,
    "['Real Estate']": 218.1,
    "['Fashion & Retail']": 948.2,
    "['Diversified']": 544.9,
    "['Finance & Investments']": 335.9,
    "['Finance and Investments']": 0.0,
    "['Healthcare']": 203.9,
    "['Energy']": 99.4,
    "['Food and Beverage']": 0.0
  },
  {
    "year": 2023,
    "filter": "all",
    "['Manufacturing']": 1025.9,
    "['Technology']": 1871.0,
    "['Real Estate']": 657.4,
    "['Fashion & Retail']": 1698.8,
    "['Diversified']": 905.2,
    "['Finance & Investments']": 1605.1,
    "['Finance and Investments']": 0.0,
    "['Healthcare']": 643.2,
    "['Energy']": 453.5,
    "['Food and Beverage']": 0.0
  },
  {
    "year": 2023,
    "filter": "self-made",
    "['Manufacturing']": 748.7,
    "['Technology']": 1752.6,
    "['Real Estate']": 432.7,
    "['Fashion & Retail']": 687.4,
    "['Diversified']": 354.2,
    "['Finance & Investments']": 1251.1,
    "['Finance and Investments']": 0.0,
    "['Healthcare']": 463.2,
    "['Energy']": 345.4,
    "['Food and Beverage']": 0.0
  },
  {
    "year": 2023,
    "filter": "inherited",
    "['Manufacturing']": 277.2,
    "['Technology']": 118.4,
    "['Real Estate']": 224.7,
    "['Fashion & Retail']": 1011.4,
    "['Diversified']": 551.0,
    "['Finance & Investments']": 354.0,
    "['Finance and Investments']": 0.0,
    "['Healthcare']": 180.0,
    "['Energy']": 108.1,
    "['Food and Beverage']": 0.0
  },
  {
    "year": 2024,
    "filter": "all",
    "['Manufacturing']": 1015.7,
    "['Technology']": 2601.7,
    "['Real Estate']": 667.1,
    "['Fashion & Retail']": 1958.2,
    "['Diversified']": 1137.0,
    "['Finance & Investments']": 2175.3,
    "['Finance and Investments']": 0.0,
    "['Healthcare']": 681.8,
    "['Energy']": 504.5,
    "['Food and Beverage']": 0.0
  },
  {
    "year": 2024,
    "filter": "self-made",
    "['Manufacturing']": 660.0,
    "['Technology']": 2430.5,
    "['Real Estate']": 427.8,
    "['Fashion & Retail']": 776.3,
    "['Diversified']": 402.1,
    "['Finance & Investments']": 1735.1,
    "['Finance and Investments']": 0.0,
    "['Healthcare']": 458.5,
    "['Energy']": 381.2,
    "['Food and Beverage']": 0.0
  },
  {
    "year": 2024,
    "filter": "inherited",
    "['Manufacturing']": 355.7,
    "['Technology']": 171.2,
    "['Real Estate']": 239.3,
    "['Fashion & Retail']": 1181.9,
    "['Diversified']": 734.9,
    "['Finance & Investments']": 440.2,
    "['Finance and Investments']": 0.0,
    "['Healthcare']": 223.3,
    "['Energy']": 123.3,
    "['Food and Beverage']": 0.0
  }
]